{
  "date": "March 24, 2026",
  "hero": {
    "text": "Believe in yourself and all that you are.",
    "author": "Christian D. Larson"
  },
  "aries": {
    "general": "Today, you may find yourself energized and ready to tackle new challenges.",
    "love": "A spark of passion may ignite in your relationship; cherish the moments.",
    "career": "Opportunities for growth and advancement are on the horizon; stay alert.",
    "luckyNumbers": "5, 7, 9"
  },
  "taurus": {
    "general": "Stability is key today; focus on maintaining equilibrium in your life.",
    "love": "Express your feelings openly to strengthen your bond with loved ones.",
    "career": "Patience and perseverance will pay off in your professional endeavors.",
    "luckyNumbers": "2, 4, 6"
  },
  "gemini": {
    "general": "Communication flows easily today; use it to your advantage.",
    "love": "Engage in deep conversations to connect with your partner on a new level.",
    "career": "Networking opportunities may arise; don’t hesitate to put yourself out there.",
    "luckyNumbers": "3, 8, 10"
  },
  "cancer": {
    "general": "Intuition will guide you; trust your instincts as you navigate the day.",
    "love": "Show your affection through small gestures; they will be deeply appreciated.",
    "career": "A creative solution may present itself; embrace it wholeheartedly.",
    "luckyNumbers": "1, 11, 12"
  },
  "leo": {
    "general": "Confidence will shine through you; harness it to inspire others.",
    "love": "A romantic surprise could make your day; enjoy the little things.",
    "career": "Your leadership skills will be recognized; take charge of new projects.",
    "luckyNumbers": "2, 6, 8"
  },
  "virgo": {
    "general": "Attention to detail will be crucial; ensure everything is in place.",
    "love": "Conversations about the future may arise; be honest about your desires.",
    "career": "Critical thinking will help you solve ongoing issues at work.",
    "luckyNumbers": "4, 9, 10"
  },
  "content": {
    "professional": [
      {
        "id": 1,
        "text": "Success usually comes to those who are too busy to be looking for it.",
        "author": "Henry David Thoreau",
        "tags": [
          "career"
        ]
      },
      {
        "id": 2,
        "text": "Opportunities don't happen. You create them.",
        "author": "Chris Grosser",
        "tags": [
          "career"
        ]
      },
      {
        "id": 3,
        "text": "It’s not about ideas. It’s about making ideas happen.",
        "author": "Scott Belsky",
        "tags": [
          "career"
        ]
      },
      {
        "id": 4,
        "text": "The future depends on what you do today.",
        "author": "Mahatma Gandhi",
        "tags": [
          "career"
        ]
      },
      {
        "id": 5,
        "text": "The only way to do great work is to love what you do.",
        "author": "Steve Jobs",
        "tags": [
          "career"
        ]
      },
      {
        "id": 6,
        "text": "Success is not the key to happiness. Happiness is the key to success.",
        "author": "Albert Schweitzer",
        "tags": [
          "career"
        ]
      }
    ],
    "motivation": [
      {
        "id": 1,
        "text": "The only limit to our realization of tomorrow will be our doubts of today.",
        "author": "Franklin D. Roosevelt",
        "tags": [
          "motivation"
        ]
      },
      {
        "id": 2,
        "text": "You are never too old to set another goal or to dream a new dream.",
        "author": "C.S. Lewis",
        "tags": [
          "motivation"
        ]
      },
      {
        "id": 3,
        "text": "Believe you can and you're halfway there.",
        "author": "Theodore Roosevelt",
        "tags": [
          "motivation"
        ]
      },
      {
        "id": 4,
        "text": "The future belongs to those who believe in the beauty of their dreams.",
        "author": "Eleanor Roosevelt",
        "tags": [
          "motivation"
        ]
      },
      {
        "id": 5,
        "text": "Success is not how high you have climbed, but how you make a positive difference to the world.",
        "author": "Roy T. Bennett",
        "tags": [
          "motivation"
        ]
      },
      {
        "id": 6,
        "text": "Don't watch the clock; do what it does. Keep going.",
        "author": "Sam Levenson",
        "tags": [
          "motivation"
        ]
      }
    ],
    "captions": [
      {
        "id": 1,
        "text": "Every moment is a fresh beginning.",
        "author": "T.S. Eliot",
        "tags": [
          "caption"
        ]
      },
      {
        "id": 2,
        "text": "Life is either a daring adventure or nothing at all.",
        "author": "Helen Keller",
        "tags": [
          "caption"
        ]
      },
      {
        "id": 3,
        "text": "The biggest adventure you can take is to live the life of your dreams.",
        "author": "Oprah Winfrey",
        "tags": [
          "caption"
        ]
      },
      {
        "id": 4,
        "text": "What lies behind us and what lies before us are tiny matters compared to what lies within us.",
        "author": "Ralph Waldo Emerson",
        "tags": [
          "caption"
        ]
      },
      {
        "id": 5,
        "text": "Turn your wounds into wisdom.",
        "author": "Oprah Winfrey",
        "tags": [
          "caption"
        ]
      },
      {
        "id": 6,
        "text": "Do one thing every day that scares you.",
        "author": "Eleanor Roosevelt",
        "tags": [
          "caption"
        ]
      }
    ],
    "tech": [
      {
        "id": 1,
        "text": "The science of today is the technology of tomorrow.",
        "author": "Edward Teller",
        "tags": [
          "tech"
        ]
      },
      {
        "id": 2,
        "text": "Technology is best when it brings people together.",
        "author": "Matt Mullenweg",
        "tags": [
          "tech"
        ]
      },
      {
        "id": 3,
        "text": "The great myth of our times is that technology is communication.",
        "author": "Libby Larsen",
        "tags": [
          "tech"
        ]
      },
      {
        "id": 4,
        "text": "Any sufficiently advanced technology is indistinguishable from magic.",
        "author": "Arthur C. Clarke",
        "tags": [
          "tech"
        ]
      },
      {
        "id": 5,
        "text": "Innovation distinguishes between a leader and a follower.",
        "author": "Steve Jobs",
        "tags": [
          "tech"
        ]
      },
      {
        "id": 6,
        "text": "The real problem is not whether machines think but whether men do.",
        "author": "B.F. Skinner",
        "tags": [
          "tech"
        ]
      }
    ],
    "fun": [
      {
        "id": 1,
        "text": "Life is too important to be taken seriously.",
        "author": "Oscar Wilde",
        "tags": [
          "fun"
        ]
      },
      {
        "id": 2,
        "text": "Laughter is an instant vacation.",
        "author": "Milton Berle",
        "tags": [
          "fun"
        ]
      },
      {
        "id": 3,
        "text": "A day without laughter is a day wasted.",
        "author": "Charlie Chaplin",
        "tags": [
          "fun"
        ]
      },
      {
        "id": 4,
        "text": "The most wasted of days is one without laughter.",
        "author": "E.E. Cummings",
        "tags": [
          "fun"
        ]
      },
      {
        "id": 5,
        "text": "Comedy is simply a funny way of being serious.",
        "author": "Peter Ustinov",
        "tags": [
          "fun"
        ]
      },
      {
        "id": 6,
        "text": "Fun is not a straight line; it’s a tangled path that goes up and down.",
        "author": "Cornelia Funke",
        "tags": [
          "fun"
        ]
      }
    ],
    "faith": [
      {
        "id": 1,
        "text": "Faith is taking the first step even when you don't see the whole staircase.",
        "author": "Martin Luther King Jr.",
        "tags": [
          "faith"
        ]
      },
      {
        "id": 2,
        "text": "Faith is the bird that feels the light when the dawn is still dark.",
        "author": "Rabindranath Tagore",
        "tags": [
          "faith"
        ]
      },
      {
        "id": 3,
        "text": "To be a Christian means to forgive the inexcusable because God has forgiven the inexcusable in you.",
        "author": "C.S. Lewis",
        "tags": [
          "faith"
        ]
      },
      {
        "id": 4,
        "text": "Faith is the assurance of things hoped for, the conviction of things not seen.",
        "author": "Hebrews 11:1",
        "tags": [
          "faith"
        ]
      },
      {
        "id": 5,
        "text": "For with God nothing shall be impossible.",
        "author": "Luke 1:37",
        "tags": [
          "faith"
        ]
      },
      {
        "id": 6,
        "text": "The greatest discovery of my generation is that a human being can alter his life by altering his attitude.",
        "author": "William James",
        "tags": [
          "faith"
        ]
      }
    ],
    "wisdom": [
      {
        "id": 1,
        "text": "The invariable mark of wisdom is to see the miraculous in the common.",
        "author": "Ralph Waldo Emerson",
        "tags": [
          "wisdom"
        ]
      },
      {
        "id": 2,
        "text": "Knowing yourself is the beginning of all wisdom.",
        "author": "Aristotle",
        "tags": [
          "wisdom"
        ]
      },
      {
        "id": 3,
        "text": "The only true wisdom is in knowing you know nothing.",
        "author": "Socrates",
        "tags": [
          "wisdom"
        ]
      },
      {
        "id": 4,
        "text": "Wisdom is not a product of schooling but of the lifelong attempt to acquire it.",
        "author": "Albert Einstein",
        "tags": [
          "wisdom"
        ]
      },
      {
        "id": 5,
        "text": "Patience is the companion of wisdom.",
        "author": "Saint Augustine",
        "tags": [
          "wisdom"
        ]
      },
      {
        "id": 6,
        "text": "Wisdom begins in wonder.",
        "author": "Socrates",
        "tags": [
          "wisdom"
        ]
      }
    ]
  }
}