{"nodes": [{"id": "c_users_williams_martins_pojetos_smartkitnow_src_components_templates_calculatorverticallayout_tsx", "label": "CalculatorVerticalLayout.tsx", "file_type": "code", "source_file": "C:\\Users\\Williams Martins\\Pojetos\\Smartkitnow\\src\\components\\templates\\CalculatorVerticalLayout.tsx", "source_location": "L1"}, {"id": "templates_calculatorverticallayout_onthispagesection", "label": "OnThisPageSection", "file_type": "code", "source_file": "C:\\Users\\Williams Martins\\Pojetos\\Smartkitnow\\src\\components\\templates\\CalculatorVerticalLayout.tsx", "source_location": "L27"}, {"id": "templates_calculatorverticallayout_onthispagenav", "label": "OnThisPageNav()", "file_type": "code", "source_file": "C:\\Users\\Williams Martins\\Pojetos\\Smartkitnow\\src\\components\\templates\\CalculatorVerticalLayout.tsx", "source_location": "L32"}, {"id": "templates_calculatorverticallayout_formulavariable", "label": "FormulaVariable", "file_type": "code", "source_file": "C:\\Users\\Williams Martins\\Pojetos\\Smartkitnow\\src\\components\\templates\\CalculatorVerticalLayout.tsx", "source_location": "L69"}, {"id": "templates_calculatorverticallayout_formulabox", "label": "FormulaBox()", "file_type": "code", "source_file": "C:\\Users\\Williams Martins\\Pojetos\\Smartkitnow\\src\\components\\templates\\CalculatorVerticalLayout.tsx", "source_location": "L74"}, {"id": "templates_calculatorverticallayout_examplestep", "label": "ExampleStep", "file_type": "code", "source_file": "C:\\Users\\Williams Martins\\Pojetos\\Smartkitnow\\src\\components\\templates\\CalculatorVerticalLayout.tsx", "source_location": "L126"}, {"id": "templates_calculatorverticallayout_examplesection", "label": "ExampleSection()", "file_type": "code", "source_file": "C:\\Users\\Williams Martins\\Pojetos\\Smartkitnow\\src\\components\\templates\\CalculatorVerticalLayout.tsx", "source_location": "L136"}, {"id": "templates_calculatorverticallayout_relatedcalc", "label": "RelatedCalc", "file_type": "code", "source_file": "C:\\Users\\Williams Martins\\Pojetos\\Smartkitnow\\src\\components\\templates\\CalculatorVerticalLayout.tsx", "source_location": "L194"}, {"id": "templates_calculatorverticallayout_relatedcalculators", "label": "RelatedCalculators()", "file_type": "code", "source_file": "C:\\Users\\Williams Martins\\Pojetos\\Smartkitnow\\src\\components\\templates\\CalculatorVerticalLayout.tsx", "source_location": "L200"}, {"id": "templates_calculatorverticallayout_calculatorverticallayoutprops", "label": "CalculatorVerticalLayoutProps", "file_type": "code", "source_file": "C:\\Users\\Williams Martins\\Pojetos\\Smartkitnow\\src\\components\\templates\\CalculatorVerticalLayout.tsx", "source_location": "L232"}, {"id": "templates_calculatorverticallayout_calculatorverticallayout", "label": "CalculatorVerticalLayout()", "file_type": "code", "source_file": "C:\\Users\\Williams Martins\\Pojetos\\Smartkitnow\\src\\components\\templates\\CalculatorVerticalLayout.tsx", "source_location": "L264"}], "edges": [{"source": "c_users_williams_martins_pojetos_smartkitnow_src_components_templates_calculatorverticallayout_tsx", "target": "react", "relation": "imports_from", "context": "import", "confidence": "EXTRACTED", "source_file": "C:\\Users\\Williams Martins\\Pojetos\\Smartkitnow\\src\\components\\templates\\CalculatorVerticalLayout.tsx", "source_location": "L1", "weight": 1.0}, {"source": "c_users_williams_martins_pojetos_smartkitnow_src_components_templates_calculatorverticallayout_tsx", "target": "react_router_dom", "relation": "imports_from", "context": "import", "confidence": "EXTRACTED", "source_file": "C:\\Users\\Williams Martins\\Pojetos\\Smartkitnow\\src\\components\\templates\\CalculatorVerticalLayout.tsx", "source_location": "L2", "weight": 1.0}, {"source": "c_users_williams_martins_pojetos_smartkitnow_src_components_templates_calculatorverticallayout_tsx", "target": "c_users_williams_martins_pojetos_smartkitnow_src_components_adunit_tsx", "relation": "imports_from", "context": "import", "confidence": "EXTRACTED", "source_file": "C:\\Users\\Williams Martins\\Pojetos\\Smartkitnow\\src\\components\\templates\\CalculatorVerticalLayout.tsx", "source_location": "L3", "weight": 1.0}, {"source": "c_users_williams_martins_pojetos_smartkitnow_src_components_templates_calculatorverticallayout_tsx", "target": "c_users_williams_martins_pojetos_smartkitnow_src_components_sharethispagebox_tsx", "relation": "imports_from", "context": "import", "confidence": "EXTRACTED", "source_file": "C:\\Users\\Williams Martins\\Pojetos\\Smartkitnow\\src\\components\\templates\\CalculatorVerticalLayout.tsx", "source_location": "L4", "weight": 1.0}, {"source": "c_users_williams_martins_pojetos_smartkitnow_src_components_templates_calculatorverticallayout_tsx", "target": "c_users_williams_martins_pojetos_smartkitnow_src_components_suggestionbox_tsx", "relation": "imports_from", "context": "import", "confidence": "EXTRACTED", "source_file": "C:\\Users\\Williams Martins\\Pojetos\\Smartkitnow\\src\\components\\templates\\CalculatorVerticalLayout.tsx", "source_location": "L5", "weight": 1.0}, {"source": "c_users_williams_martins_pojetos_smartkitnow_src_components_templates_calculatorverticallayout_tsx", "target": "c_users_williams_martins_pojetos_smartkitnow_src_components_legaldisclaimer_tsx", "relation": "imports_from", "context": "import", "confidence": "EXTRACTED", "source_file": "C:\\Users\\Williams Martins\\Pojetos\\Smartkitnow\\src\\components\\templates\\CalculatorVerticalLayout.tsx", "source_location": "L6", "weight": 1.0}, {"source": "c_users_williams_martins_pojetos_smartkitnow_src_components_templates_calculatorverticallayout_tsx", "target": "c_users_williams_martins_pojetos_smartkitnow_src_data_calculatorregistry_ts", "relation": "imports_from", "context": "import", "confidence": "EXTRACTED", "source_file": "C:\\Users\\Williams Martins\\Pojetos\\Smartkitnow\\src\\components\\templates\\CalculatorVerticalLayout.tsx", "source_location": "L7", "weight": 1.0}, {"source": "c_users_williams_martins_pojetos_smartkitnow_src_components_templates_calculatorverticallayout_tsx", "target": "data_calculatorregistry_getentry", "relation": "imports", "context": "import", "confidence": "EXTRACTED", "source_file": "C:\\Users\\Williams Martins\\Pojetos\\Smartkitnow\\src\\components\\templates\\CalculatorVerticalLayout.tsx", "source_location": "L7", "weight": 1.0}, {"source": "c_users_williams_martins_pojetos_smartkitnow_src_components_templates_calculatorverticallayout_tsx", "target": "c_users_williams_martins_pojetos_smartkitnow_src_components_seohead_tsx", "relation": "imports_from", "context": "import", "confidence": "EXTRACTED", "source_file": "C:\\Users\\Williams Martins\\Pojetos\\Smartkitnow\\src\\components\\templates\\CalculatorVerticalLayout.tsx", "source_location": "L8", "weight": 1.0}, {"source": "c_users_williams_martins_pojetos_smartkitnow_src_components_templates_calculatorverticallayout_tsx", "target": "c_users_williams_martins_pojetos_smartkitnow_src_components_relatedcalculators_tsx", "relation": "imports_from", "context": "import", "confidence": "EXTRACTED", "source_file": "C:\\Users\\Williams Martins\\Pojetos\\Smartkitnow\\src\\components\\templates\\CalculatorVerticalLayout.tsx", "source_location": "L9", "weight": 1.0}, {"source": "c_users_williams_martins_pojetos_smartkitnow_src_components_templates_calculatorverticallayout_tsx", "target": "c_users_williams_martins_pojetos_smartkitnow_src_data_categorymeta_ts", "relation": "imports_from", "context": "import", "confidence": "EXTRACTED", "source_file": "C:\\Users\\Williams Martins\\Pojetos\\Smartkitnow\\src\\components\\templates\\CalculatorVerticalLayout.tsx", "source_location": "L10", "weight": 1.0}, {"source": "c_users_williams_martins_pojetos_smartkitnow_src_components_templates_calculatorverticallayout_tsx", "target": "data_categorymeta_categories", "relation": "imports", "context": "import", "confidence": "EXTRACTED", "source_file": "C:\\Users\\Williams Martins\\Pojetos\\Smartkitnow\\src\\components\\templates\\CalculatorVerticalLayout.tsx", "source_location": "L10", "weight": 1.0}, {"source": "c_users_williams_martins_pojetos_smartkitnow_src_components_templates_calculatorverticallayout_tsx", "target": "react_helmet_async", "relation": "imports_from", "context": "import", "confidence": "EXTRACTED", "source_file": "C:\\Users\\Williams Martins\\Pojetos\\Smartkitnow\\src\\components\\templates\\CalculatorVerticalLayout.tsx", "source_location": "L11", "weight": 1.0}, {"source": "c_users_williams_martins_pojetos_smartkitnow_src_components_templates_calculatorverticallayout_tsx", "target": "templates_calculatorverticallayout_onthispagesection", "relation": "contains", "confidence": "EXTRACTED", "source_file": "C:\\Users\\Williams Martins\\Pojetos\\Smartkitnow\\src\\components\\templates\\CalculatorVerticalLayout.tsx", "source_location": "L27", "weight": 1.0}, {"source": "c_users_williams_martins_pojetos_smartkitnow_src_components_templates_calculatorverticallayout_tsx", "target": "templates_calculatorverticallayout_onthispagenav", "relation": "contains", "confidence": "EXTRACTED", "source_file": "C:\\Users\\Williams Martins\\Pojetos\\Smartkitnow\\src\\components\\templates\\CalculatorVerticalLayout.tsx", "source_location": "L32", "weight": 1.0}, {"source": "c_users_williams_martins_pojetos_smartkitnow_src_components_templates_calculatorverticallayout_tsx", "target": "templates_calculatorverticallayout_formulavariable", "relation": "contains", "confidence": "EXTRACTED", "source_file": "C:\\Users\\Williams Martins\\Pojetos\\Smartkitnow\\src\\components\\templates\\CalculatorVerticalLayout.tsx", "source_location": "L69", "weight": 1.0}, {"source": "c_users_williams_martins_pojetos_smartkitnow_src_components_templates_calculatorverticallayout_tsx", "target": "templates_calculatorverticallayout_formulabox", "relation": "contains", "confidence": "EXTRACTED", "source_file": "C:\\Users\\Williams Martins\\Pojetos\\Smartkitnow\\src\\components\\templates\\CalculatorVerticalLayout.tsx", "source_location": "L74", "weight": 1.0}, {"source": "c_users_williams_martins_pojetos_smartkitnow_src_components_templates_calculatorverticallayout_tsx", "target": "templates_calculatorverticallayout_examplestep", "relation": "contains", "confidence": "EXTRACTED", "source_file": "C:\\Users\\Williams Martins\\Pojetos\\Smartkitnow\\src\\components\\templates\\CalculatorVerticalLayout.tsx", "source_location": "L126", "weight": 1.0}, {"source": "c_users_williams_martins_pojetos_smartkitnow_src_components_templates_calculatorverticallayout_tsx", "target": "templates_calculatorverticallayout_examplesection", "relation": "contains", "confidence": "EXTRACTED", "source_file": "C:\\Users\\Williams Martins\\Pojetos\\Smartkitnow\\src\\components\\templates\\CalculatorVerticalLayout.tsx", "source_location": "L136", "weight": 1.0}, {"source": "c_users_williams_martins_pojetos_smartkitnow_src_components_templates_calculatorverticallayout_tsx", "target": "templates_calculatorverticallayout_relatedcalc", "relation": "contains", "confidence": "EXTRACTED", "source_file": "C:\\Users\\Williams Martins\\Pojetos\\Smartkitnow\\src\\components\\templates\\CalculatorVerticalLayout.tsx", "source_location": "L194", "weight": 1.0}, {"source": "c_users_williams_martins_pojetos_smartkitnow_src_components_templates_calculatorverticallayout_tsx", "target": "templates_calculatorverticallayout_relatedcalculators", "relation": "contains", "confidence": "EXTRACTED", "source_file": "C:\\Users\\Williams Martins\\Pojetos\\Smartkitnow\\src\\components\\templates\\CalculatorVerticalLayout.tsx", "source_location": "L200", "weight": 1.0}, {"source": "c_users_williams_martins_pojetos_smartkitnow_src_components_templates_calculatorverticallayout_tsx", "target": "templates_calculatorverticallayout_calculatorverticallayoutprops", "relation": "contains", "confidence": "EXTRACTED", "source_file": "C:\\Users\\Williams Martins\\Pojetos\\Smartkitnow\\src\\components\\templates\\CalculatorVerticalLayout.tsx", "source_location": "L232", "weight": 1.0}, {"source": "c_users_williams_martins_pojetos_smartkitnow_src_components_templates_calculatorverticallayout_tsx", "target": "templates_calculatorverticallayout_calculatorverticallayout", "relation": "contains", "confidence": "EXTRACTED", "source_file": "C:\\Users\\Williams Martins\\Pojetos\\Smartkitnow\\src\\components\\templates\\CalculatorVerticalLayout.tsx", "source_location": "L264", "weight": 1.0}], "raw_calls": [{"caller_nid": "templates_calculatorverticallayout_onthispagenav", "callee": "map", "is_member_call": true, "source_file": "C:\\Users\\Williams Martins\\Pojetos\\Smartkitnow\\src\\components\\templates\\CalculatorVerticalLayout.tsx", "source_location": "L50"}, {"caller_nid": "templates_calculatorverticallayout_formulabox", "callee": "map", "is_member_call": true, "source_file": "C:\\Users\\Williams Martins\\Pojetos\\Smartkitnow\\src\\components\\templates\\CalculatorVerticalLayout.tsx", "source_location": "L107"}, {"caller_nid": "templates_calculatorverticallayout_examplesection", "callee": "trim", "is_member_call": true, "source_file": "C:\\Users\\Williams Martins\\Pojetos\\Smartkitnow\\src\\components\\templates\\CalculatorVerticalLayout.tsx", "source_location": "L147"}, {"caller_nid": "templates_calculatorverticallayout_examplesection", "callee": "map", "is_member_call": true, "source_file": "C:\\Users\\Williams Martins\\Pojetos\\Smartkitnow\\src\\components\\templates\\CalculatorVerticalLayout.tsx", "source_location": "L160"}, {"caller_nid": "templates_calculatorverticallayout_relatedcalculators", "callee": "map", "is_member_call": true, "source_file": "C:\\Users\\Williams Martins\\Pojetos\\Smartkitnow\\src\\components\\templates\\CalculatorVerticalLayout.tsx", "source_location": "L209"}, {"caller_nid": "templates_calculatorverticallayout_calculatorverticallayout", "callee": "useLocation", "is_member_call": false, "source_file": "C:\\Users\\Williams Martins\\Pojetos\\Smartkitnow\\src\\components\\templates\\CalculatorVerticalLayout.tsx", "source_location": "L283"}, {"caller_nid": "templates_calculatorverticallayout_calculatorverticallayout", "callee": "useMemo", "is_member_call": false, "source_file": "C:\\Users\\Williams Martins\\Pojetos\\Smartkitnow\\src\\components\\templates\\CalculatorVerticalLayout.tsx", "source_location": "L284"}, {"caller_nid": "templates_calculatorverticallayout_calculatorverticallayout", "callee": "filter", "is_member_call": true, "source_file": "C:\\Users\\Williams Martins\\Pojetos\\Smartkitnow\\src\\components\\templates\\CalculatorVerticalLayout.tsx", "source_location": "L288"}, {"caller_nid": "templates_calculatorverticallayout_calculatorverticallayout", "callee": "split", "is_member_call": true, "source_file": "C:\\Users\\Williams Martins\\Pojetos\\Smartkitnow\\src\\components\\templates\\CalculatorVerticalLayout.tsx", "source_location": "L288"}, {"caller_nid": "templates_calculatorverticallayout_calculatorverticallayout", "callee": "pop", "is_member_call": true, "source_file": "C:\\Users\\Williams Martins\\Pojetos\\Smartkitnow\\src\\components\\templates\\CalculatorVerticalLayout.tsx", "source_location": "L289"}, {"caller_nid": "templates_calculatorverticallayout_calculatorverticallayout", "callee": "getEntry", "is_member_call": false, "source_file": "C:\\Users\\Williams Martins\\Pojetos\\Smartkitnow\\src\\components\\templates\\CalculatorVerticalLayout.tsx", "source_location": "L290"}, {"caller_nid": "templates_calculatorverticallayout_calculatorverticallayout", "callee": "useRef", "is_member_call": false, "source_file": "C:\\Users\\Williams Martins\\Pojetos\\Smartkitnow\\src\\components\\templates\\CalculatorVerticalLayout.tsx", "source_location": "L293"}, {"caller_nid": "templates_calculatorverticallayout_calculatorverticallayout", "callee": "useState", "is_member_call": false, "source_file": "C:\\Users\\Williams Martins\\Pojetos\\Smartkitnow\\src\\components\\templates\\CalculatorVerticalLayout.tsx", "source_location": "L294"}, {"caller_nid": "templates_calculatorverticallayout_calculatorverticallayout", "callee": "useEffect", "is_member_call": false, "source_file": "C:\\Users\\Williams Martins\\Pojetos\\Smartkitnow\\src\\components\\templates\\CalculatorVerticalLayout.tsx", "source_location": "L296"}, {"caller_nid": "templates_calculatorverticallayout_calculatorverticallayout", "callee": "stringify", "is_member_call": true, "source_file": "C:\\Users\\Williams Martins\\Pojetos\\Smartkitnow\\src\\components\\templates\\CalculatorVerticalLayout.tsx", "source_location": "L331"}, {"caller_nid": "templates_calculatorverticallayout_calculatorverticallayout", "callee": "(() => {\r\n                    const catMeta = CATEGORIES[entry.category];\r\n                    const catPath = catMeta?.path ?? entry.category;\r\n                    const catLabel = catMeta?.display ?? entry.category.replace(/-/g, \" \").replace(/\\b\\w/g, s => s.toUpperCase());\r\n                    return (\r\n                      <>\r\n                        <li aria-hidden>/</li>\r\n                        <li>\r\n                          <Link to={`/${catPath}`} className=\"hover:text-primary transition-colors\">{catLabel}</Link>\r\n                        </li>\r\n                      </>\r\n                    );\r\n                  })", "is_member_call": false, "source_file": "C:\\Users\\Williams Martins\\Pojetos\\Smartkitnow\\src\\components\\templates\\CalculatorVerticalLayout.tsx", "source_location": "L355"}]}