{"nodes": [{"id": "c_users_williams_martins_pojetos_smartkitnow_src_components_games_brickdashgame_tsx", "label": "BrickDashGame.tsx", "file_type": "code", "source_file": "C:\\Users\\Williams Martins\\Pojetos\\Smartkitnow\\src\\components\\games\\BrickDashGame.tsx", "source_location": "L1"}, {"id": "games_brickdashgame_difficulty", "label": "Difficulty", "file_type": "code", "source_file": "C:\\Users\\Williams Martins\\Pojetos\\Smartkitnow\\src\\components\\games\\BrickDashGame.tsx", "source_location": "L13"}, {"id": "games_brickdashgame_difficulty_settings", "label": "DIFFICULTY_SETTINGS", "file_type": "code", "source_file": "C:\\Users\\Williams Martins\\Pojetos\\Smartkitnow\\src\\components\\games\\BrickDashGame.tsx", "source_location": "L15"}, {"id": "games_brickdashgame_obstacle", "label": "Obstacle", "file_type": "code", "source_file": "C:\\Users\\Williams Martins\\Pojetos\\Smartkitnow\\src\\components\\games\\BrickDashGame.tsx", "source_location": "L21"}, {"id": "games_brickdashgame_brickdashgame", "label": "BrickDashGame()", "file_type": "code", "source_file": "C:\\Users\\Williams Martins\\Pojetos\\Smartkitnow\\src\\components\\games\\BrickDashGame.tsx", "source_location": "L30"}], "edges": [{"source": "c_users_williams_martins_pojetos_smartkitnow_src_components_games_brickdashgame_tsx", "target": "react", "relation": "imports_from", "context": "import", "confidence": "EXTRACTED", "source_file": "C:\\Users\\Williams Martins\\Pojetos\\Smartkitnow\\src\\components\\games\\BrickDashGame.tsx", "source_location": "L1", "weight": 1.0}, {"source": "c_users_williams_martins_pojetos_smartkitnow_src_components_games_brickdashgame_tsx", "target": "c_users_williams_martins_pojetos_smartkitnow_src_components_templates_calculatorverticallayout_tsx", "relation": "imports_from", "context": "import", "confidence": "EXTRACTED", "source_file": "C:\\Users\\Williams Martins\\Pojetos\\Smartkitnow\\src\\components\\games\\BrickDashGame.tsx", "source_location": "L2", "weight": 1.0}, {"source": "c_users_williams_martins_pojetos_smartkitnow_src_components_games_brickdashgame_tsx", "target": "c_users_williams_martins_pojetos_smartkitnow_src_components_ui_button_tsx", "relation": "imports_from", "context": "import", "confidence": "EXTRACTED", "source_file": "C:\\Users\\Williams Martins\\Pojetos\\Smartkitnow\\src\\components\\games\\BrickDashGame.tsx", "source_location": "L3", "weight": 1.0}, {"source": "c_users_williams_martins_pojetos_smartkitnow_src_components_games_brickdashgame_tsx", "target": "ui_button_button", "relation": "imports", "context": "import", "confidence": "EXTRACTED", "source_file": "C:\\Users\\Williams Martins\\Pojetos\\Smartkitnow\\src\\components\\games\\BrickDashGame.tsx", "source_location": "L3", "weight": 1.0}, {"source": "c_users_williams_martins_pojetos_smartkitnow_src_components_games_brickdashgame_tsx", "target": "lucide_react", "relation": "imports_from", "context": "import", "confidence": "EXTRACTED", "source_file": "C:\\Users\\Williams Martins\\Pojetos\\Smartkitnow\\src\\components\\games\\BrickDashGame.tsx", "source_location": "L4", "weight": 1.0}, {"source": "c_users_williams_martins_pojetos_smartkitnow_src_components_games_brickdashgame_tsx", "target": "c_users_williams_martins_pojetos_smartkitnow_src_components_games_gamestartoverlay_tsx", "relation": "imports_from", "context": "import", "confidence": "EXTRACTED", "source_file": "C:\\Users\\Williams Martins\\Pojetos\\Smartkitnow\\src\\components\\games\\BrickDashGame.tsx", "source_location": "L5", "weight": 1.0}, {"source": "c_users_williams_martins_pojetos_smartkitnow_src_components_games_brickdashgame_tsx", "target": "games_brickdashgame_difficulty", "relation": "contains", "confidence": "EXTRACTED", "source_file": "C:\\Users\\Williams Martins\\Pojetos\\Smartkitnow\\src\\components\\games\\BrickDashGame.tsx", "source_location": "L13", "weight": 1.0}, {"source": "c_users_williams_martins_pojetos_smartkitnow_src_components_games_brickdashgame_tsx", "target": "games_brickdashgame_difficulty_settings", "relation": "contains", "confidence": "EXTRACTED", "source_file": "C:\\Users\\Williams Martins\\Pojetos\\Smartkitnow\\src\\components\\games\\BrickDashGame.tsx", "source_location": "L15", "weight": 1.0}, {"source": "c_users_williams_martins_pojetos_smartkitnow_src_components_games_brickdashgame_tsx", "target": "games_brickdashgame_obstacle", "relation": "contains", "confidence": "EXTRACTED", "source_file": "C:\\Users\\Williams Martins\\Pojetos\\Smartkitnow\\src\\components\\games\\BrickDashGame.tsx", "source_location": "L21", "weight": 1.0}, {"source": "c_users_williams_martins_pojetos_smartkitnow_src_components_games_brickdashgame_tsx", "target": "games_brickdashgame_brickdashgame", "relation": "contains", "confidence": "EXTRACTED", "source_file": "C:\\Users\\Williams Martins\\Pojetos\\Smartkitnow\\src\\components\\games\\BrickDashGame.tsx", "source_location": "L30", "weight": 1.0}], "raw_calls": [{"caller_nid": "games_brickdashgame_brickdashgame", "callee": "useRef", "is_member_call": false, "source_file": "C:\\Users\\Williams Martins\\Pojetos\\Smartkitnow\\src\\components\\games\\BrickDashGame.tsx", "source_location": "L38"}, {"caller_nid": "games_brickdashgame_brickdashgame", "callee": "useRef", "is_member_call": false, "source_file": "C:\\Users\\Williams Martins\\Pojetos\\Smartkitnow\\src\\components\\games\\BrickDashGame.tsx", "source_location": "L39"}, {"caller_nid": "games_brickdashgame_brickdashgame", "callee": "useState", "is_member_call": false, "source_file": "C:\\Users\\Williams Martins\\Pojetos\\Smartkitnow\\src\\components\\games\\BrickDashGame.tsx", "source_location": "L40"}, {"caller_nid": "games_brickdashgame_brickdashgame", "callee": "useState", "is_member_call": false, "source_file": "C:\\Users\\Williams Martins\\Pojetos\\Smartkitnow\\src\\components\\games\\BrickDashGame.tsx", "source_location": "L41"}, {"caller_nid": "games_brickdashgame_brickdashgame", "callee": "useState", "is_member_call": false, "source_file": "C:\\Users\\Williams Martins\\Pojetos\\Smartkitnow\\src\\components\\games\\BrickDashGame.tsx", "source_location": "L42"}, {"caller_nid": "games_brickdashgame_brickdashgame", "callee": "useState", "is_member_call": false, "source_file": "C:\\Users\\Williams Martins\\Pojetos\\Smartkitnow\\src\\components\\games\\BrickDashGame.tsx", "source_location": "L43"}, {"caller_nid": "games_brickdashgame_brickdashgame", "callee": "useState", "is_member_call": false, "source_file": "C:\\Users\\Williams Martins\\Pojetos\\Smartkitnow\\src\\components\\games\\BrickDashGame.tsx", "source_location": "L44"}, {"caller_nid": "games_brickdashgame_brickdashgame", "callee": "useState", "is_member_call": false, "source_file": "C:\\Users\\Williams Martins\\Pojetos\\Smartkitnow\\src\\components\\games\\BrickDashGame.tsx", "source_location": "L45"}, {"caller_nid": "games_brickdashgame_brickdashgame", "callee": "useRef", "is_member_call": false, "source_file": "C:\\Users\\Williams Martins\\Pojetos\\Smartkitnow\\src\\components\\games\\BrickDashGame.tsx", "source_location": "L48"}, {"caller_nid": "games_brickdashgame_brickdashgame", "callee": "useRef", "is_member_call": false, "source_file": "C:\\Users\\Williams Martins\\Pojetos\\Smartkitnow\\src\\components\\games\\BrickDashGame.tsx", "source_location": "L68"}, {"caller_nid": "games_brickdashgame_brickdashgame", "callee": "useEffect", "is_member_call": false, "source_file": "C:\\Users\\Williams Martins\\Pojetos\\Smartkitnow\\src\\components\\games\\BrickDashGame.tsx", "source_location": "L106"}, {"caller_nid": "games_brickdashgame_brickdashgame", "callee": "useEffect", "is_member_call": false, "source_file": "C:\\Users\\Williams Martins\\Pojetos\\Smartkitnow\\src\\components\\games\\BrickDashGame.tsx", "source_location": "L115"}, {"caller_nid": "games_brickdashgame_brickdashgame", "callee": "useCallback", "is_member_call": false, "source_file": "C:\\Users\\Williams Martins\\Pojetos\\Smartkitnow\\src\\components\\games\\BrickDashGame.tsx", "source_location": "L128"}, {"caller_nid": "games_brickdashgame_brickdashgame", "callee": "useEffect", "is_member_call": false, "source_file": "C:\\Users\\Williams Martins\\Pojetos\\Smartkitnow\\src\\components\\games\\BrickDashGame.tsx", "source_location": "L279"}, {"caller_nid": "games_brickdashgame_brickdashgame", "callee": "useEffect", "is_member_call": false, "source_file": "C:\\Users\\Williams Martins\\Pojetos\\Smartkitnow\\src\\components\\games\\BrickDashGame.tsx", "source_location": "L287"}]}